pypools/__init__.py
pypools/abstract.py
pypools/memory.py
pypools/options.py
pypools/redis.py
pypools/sqlite.py
pypools/resources/__init__.py
pypools/resources/abstract.py
pypools/resources/memory.py
pypools/resources/redis.py
pypools/resources/sqlite.py
pypools-0.1.0.dist-info/LICENSE
pypools-0.1.0.dist-info/METADATA
pypools-0.1.0.dist-info/WHEEL
pypools-0.1.0.dist-info/top_level.txt
pypools-0.1.0.dist-info/RECORD
